openai_simple_rerank/__init__.py
openai_simple_rerank/base.py
openai_simple_rerank/settings.py
openai_simple_rerank/utils.py
openai_simple_rerank-0.1.3.dist-info/licenses/LICENSE
openai_simple_rerank-0.1.3.dist-info/METADATA
openai_simple_rerank-0.1.3.dist-info/WHEEL
openai_simple_rerank-0.1.3.dist-info/top_level.txt
openai_simple_rerank-0.1.3.dist-info/RECORD
