Metadata-Version: 2.4
Name: openai-simple-rerank
Version: 0.1.3
Summary: 一个简单的rank模型的OPENAI兼容API服务的客户端访问工具。
Author: rRR0VrFP
Maintainer: rRR0VrFP
License: Apache License, Version 2.0
Keywords: openai-simple-rerank
Classifier: Development Status :: 5 - Production/Stable
Classifier: Intended Audience :: Developers
Classifier: Topic :: Software Development :: Libraries :: Python Modules
Classifier: License :: OSI Approved :: Apache Software License
Classifier: Programming Language :: Python :: 3
Classifier: Programming Language :: Python :: 3 :: Only
License-File: LICENSE
Requires-Dist: openai
Requires-Dist: requests
Requires-Dist: python-environment-settings
Dynamic: author
Dynamic: classifier
Dynamic: description
Dynamic: description-content-type
Dynamic: keywords
Dynamic: license
Dynamic: license-file
Dynamic: maintainer
Dynamic: requires-dist
Dynamic: summary
